{"name":"Granota","tagline":"A multilingual IRC bot","body":"### Welcome to Granota web page\r\nThis page is only a directory of useful pages about Granota\r\n* Granota documentation [English](http://wikicatbots.tk/wiki/Granota), [Español](http://wikicatbots.tk/wiki/Granota/es), [Català](http://wikicatbots.tk/wiki/Granota/ca).\r\n* CatBots official web page: [catbots.tk](http://catbots.tk/)\r\n\r\n[Connect to our IRC channel and see Granota \"in action\"!](https://kiwiirc.com/client/irc.lizardirc.org/catbots)","google":"","note":"Don't delete this file! It's used internally to help with page regeneration."}